classifier/__init__.py
classifier/admin.py
classifier/apps.py
classifier/classify.py
classifier/models.py
classifier/urls.py
classifier/views.py
classifier/management/__init__.py
classifier/management/commands/__init__.py
classifier/management/commands/train.py
classifier/migrations/0001_initial.py
classifier/migrations/0002_auto_20210314_2223.py
classifier/migrations/__init__.py
django_spam_classifier-0.1.2.dist-info/LICENSE
django_spam_classifier-0.1.2.dist-info/METADATA
django_spam_classifier-0.1.2.dist-info/WHEEL
django_spam_classifier-0.1.2.dist-info/top_level.txt
django_spam_classifier-0.1.2.dist-info/RECORD
