Metadata-Version: 2.1
Name: django-spam-classifier
Version: 0.1.2
Summary: Classify contact form messages as spam or not.
Home-page: https://gitlab.com/sturm/django-spam-classifier
Author: Ben Sturmfels
Author-email: ben@sturm.com.au
Project-URL: Source, https://gitlab.com/sturm/django-spam-classifier
Project-URL: Bug Reports, https://gitlab.com/sturm/django-spam-classifier/-/issues
Classifier: Development Status :: 7 - Inactive
Classifier: Intended Audience :: Developers
Classifier: License :: OSI Approved :: Apache Software License
Classifier: Programming Language :: Python :: 3
Requires-Python: >=3.6
License-File: LICENSE
Requires-Dist: Django >=4.0
